argscape/__init__.py
argscape/cli.py
argscape/load_cli.py
argscape/spatial_cli.py
argscape/vis_cli.py
argscape/api/__init__.py
argscape/api/constants.py
argscape/api/dev_storage_override.py
argscape/api/environment.yml
argscape/api/main.py
argscape/api/startup.py
argscape/api/core/__init__.py
argscape/api/core/dependencies.py
argscape/api/geo_utils/__init__.py
argscape/api/geo_utils/crs.py
argscape/api/geo_utils/crs_detect.py
argscape/api/geo_utils/fallbacks.py
argscape/api/geo_utils/io.py
argscape/api/geo_utils/land_detect.py
argscape/api/geo_utils/placement.py
argscape/api/geo_utils/shapes.py
argscape/api/geo_utils/spatial_index.py
argscape/api/geo_utils/transform.py
argscape/api/geo_utils/tree_sequence.py
argscape/api/geo_utils/data/eastern_hemisphere.geojson
argscape/api/geo_utils/data/ne_110m_land/ne_110m_land.cpg
argscape/api/geo_utils/data/ne_110m_land/ne_110m_land.dbf
argscape/api/geo_utils/data/ne_110m_land/ne_110m_land.prj
argscape/api/geo_utils/data/ne_110m_land/ne_110m_land.shp
argscape/api/geo_utils/data/ne_110m_land/ne_110m_land.shx
argscape/api/inference/__init__.py
argscape/api/inference/location_inference.py
argscape/api/inference/midpoint_inference.py
argscape/api/inference/spacetrees_inference.py
argscape/api/inference/sparg_inference.py
argscape/api/inference/temporal_inference.py
argscape/api/inference/spacetrees/__init__.py
argscape/api/inference/spacetrees/utils.py
argscape/api/inference/sparg/__init__.py
argscape/api/inference/sparg/algorithm.py
argscape/api/models/__init__.py
argscape/api/models/requests.py
argscape/api/routes/__init__.py
argscape/api/routes/downloads.py
argscape/api/routes/geographic.py
argscape/api/routes/inference.py
argscape/api/routes/sessions.py
argscape/api/routes/tree_sequences.py
argscape/api/routes/utils.py
argscape/api/services/__init__.py
argscape/api/services/graph_cache.py
argscape/api/services/graph_utils.py
argscape/api/services/session_storage.py
argscape/api/services/spatial_generation.py
argscape-0.5.0.dist-info/licenses/LICENSE
argscape-0.5.0.dist-info/METADATA
argscape-0.5.0.dist-info/WHEEL
argscape-0.5.0.dist-info/entry_points.txt
argscape-0.5.0.dist-info/top_level.txt
argscape-0.5.0.dist-info/RECORD
