Metadata-Version: 2.4
Name: argscape
Version: 0.5.0
Summary: ARGscape: interactive ARG visualization and analysis
Author-email: Chris Talbot <cat267@cornell.edu>
License-Expression: MIT
Project-URL: Homepage, https://argscape.com
Project-URL: Documentation, https://argscape.com
Project-URL: Repository, https://github.com/chris-a-talbot/argscape
Project-URL: Paper, https://arxiv.org/abs/2510.07255
Keywords: ARG,ancestral recombination graph,tree sequence,population genetics,visualization,spatial inference,temporal inference
Classifier: Development Status :: 4 - Beta
Classifier: Intended Audience :: Science/Research
Classifier: Operating System :: OS Independent
Classifier: Programming Language :: Python :: 3
Classifier: Programming Language :: Python :: 3.8
Classifier: Programming Language :: Python :: 3.9
Classifier: Programming Language :: Python :: 3.10
Classifier: Programming Language :: Python :: 3.11
Classifier: Topic :: Scientific/Engineering :: Bio-Informatics
Classifier: Topic :: Scientific/Engineering :: Visualization
Requires-Python: >=3.8
License-File: LICENSE
Requires-Dist: numpy<2.0.0,>=1.24.0
Requires-Dist: pandas
Requires-Dist: tskit
Requires-Dist: tszip>=0.2.3
Requires-Dist: msprime
Requires-Dist: scikit-learn
Requires-Dist: fastapi
Requires-Dist: uvicorn[standard]==0.24.0
Requires-Dist: python-multipart==0.0.6
Requires-Dist: python-dotenv==1.0.0
Requires-Dist: apscheduler==3.10.4
Requires-Dist: cryptography>=41.0.0
Requires-Dist: tsdate
Requires-Dist: fastgaia
Requires-Dist: geoancestry
Requires-Dist: geopandas==0.14.1
Requires-Dist: shapely<3.0.0,>=2.0.2
Requires-Dist: pyproj
Requires-Dist: fiona==1.9.5
Requires-Dist: sympy
Requires-Dist: scipy
Requires-Dist: tqdm
Requires-Dist: matplotlib
Requires-Dist: pydantic
Dynamic: license-file
